draft_basic/__init__.py
draft_basic/activation_function.py
draft_basic/basic_function.py
draft_basic/example_dataset.py
draft_basic/graph.py
draft_basic/metrics.py
draft_basic/ml_basic.py
draft_basic/neuralnetwork.py
draft_basic/preprocess.py
draft_basic/pretreat.py
draft_basic-0.19.1.dist-info/LICENSE
draft_basic-0.19.1.dist-info/METADATA
draft_basic-0.19.1.dist-info/WHEEL
draft_basic-0.19.1.dist-info/top_level.txt
draft_basic-0.19.1.dist-info/RECORD
