Metadata-Version: 2.1
Name: draft-basic
Version: 0.19.1
Summary: machine learning third-party library made by ycsyrc
Home-page: https://github.com/ycsyrc-official/draft-basic
Author: ycsyrc
Author-email: ycsyrc_tech@163.com
License: Apache-2.0 license
Project-URL: Bug Tracker, https://github.com/ycsyrc-official/draft-basic/issues
Project-URL: Documentation, https://github.com/ycsyrc-official/draft-basic/blob/main/README.md
Project-URL: Source Code, https://github.com/ycsyrc-official/draft-basic
Project-URL: Homepage, https://github.com/ycsyrc-official/draft-basic
Platform: any
Requires-Python: >=3.6
License-File: LICENSE
Requires-Dist: tqdm
Requires-Dist: numpy
Requires-Dist: matplotlib
